dqfuns/__init__.py
dqfuns/completeness.py
dqfuns/data/__init__.py
dqfuns/data/signal_gen.py
dqfuns/data/waves.py
dqfuns/features/__init__.py
dqfuns/features/utils.py
dqfuns/notebooks/Oscillation detector (Example).ipynb
dqfuns/oscillations.py
dqfuns/visualization/__init__.py
dqfuns/visualization/oscillations.py
cognite_dqfuns-0.1.0.dist-info/WHEEL
cognite_dqfuns-0.1.0.dist-info/METADATA
cognite_dqfuns-0.1.0.dist-info/RECORD
