Metadata-Version: 2.1
Name: cognite-dqfuns
Version: 0.1.0
Summary: Collection of python algorithms to evaluate data quality in CDF timeseries and assets
Author: cognite
Author-email: support@cognite.com
Requires-Python: >=3.7,<4.0
Classifier: Programming Language :: Python :: 3
Classifier: Programming Language :: Python :: 3.7
Classifier: Programming Language :: Python :: 3.8
Requires-Dist: cognite-sdk (>=1.6.0,<2.0.0)
Requires-Dist: cognite-sdk-experimental (>=0.11.1,<0.12.0)
Requires-Dist: ipykernel (>=5.2.1,<6.0.0)
Requires-Dist: jupyter (>=1.0.0,<2.0.0)
Requires-Dist: matplotlib (>=3.2.1,<4.0.0)
Requires-Dist: numba (==0.48.0)
Requires-Dist: scipy (>=1.4.1,<2.0.0)
